sharkbite/__init__.py
sharkbite/pysharkbite.cpython-36m-x86_64-linux-gnu.so
sharkbite/torch.py
sharkbite-1.2.0.3.dist-info/LICENSE
sharkbite-1.2.0.3.dist-info/METADATA
sharkbite-1.2.0.3.dist-info/WHEEL
sharkbite-1.2.0.3.dist-info/top_level.txt
sharkbite-1.2.0.3.dist-info/RECORD
