Metadata-Version: 2.1
Name: sharkbite
Version: 1.2.0.3
Summary: Apache Accumulo and Apache HDFS Python Connector
Home-page: https://docs.sharkbite.io/
Author: Marc Parisi
Author-email: phrocker@apache.org
License: UNKNOWN
Platform: UNKNOWN
Classifier: Programming Language :: C++
Classifier: License :: OSI Approved :: Apache Software License
Classifier: Operating System :: POSIX :: Linux
Requires-Python: >=3.6
